hyprwallpaper/__init__.py
hyprwallpaper/__main__.py
hyprwallpaper-1.2.0.dist-info/METADATA
hyprwallpaper-1.2.0.dist-info/WHEEL
hyprwallpaper-1.2.0.dist-info/licenses/LICENSE
hyprwallpaper-1.2.0.dist-info/RECORD
