Metadata-Version: 2.3
Name: hyprwallpaper
Version: 1.2.0
Summary: wallpaper management program for hyprland
Project-URL: Homepage, https://github.com/pseudoisomer/hyprwallpaper
Project-URL: Issues, https://github.com/pseudoisomer/pseudoisomer/hyprwallpaper/issues
Author: pseudoisomer
License-File: LICENSE
Classifier: License :: OSI Approved :: MIT License
Classifier: Operating System :: OS Independent
Classifier: Programming Language :: Python :: 3
Requires-Python: >=3.8
